circle_triangle.py
circle_triangle-1.0.0.dist-info/METADATA
circle_triangle-1.0.0.dist-info/WHEEL
circle_triangle-1.0.0.dist-info/RECORD
