Metadata-Version: 2.1
Name: circle-triangle
Version: 1.0.0
Summary: A simple package for circles and triangles
License: MIT
Author: Matvei2002
Author-email: mkozlov116@gmail.com
Requires-Python: >=3.12,<4.0
Classifier: License :: OSI Approved :: MIT License
Classifier: Programming Language :: Python :: 3
